rower/__init__.py
rower/base.py
rower/data_package.py
rower/updating.py
rower/data/ecoinvent 3.3 apos/activity_mapping.json
rower/data/ecoinvent 3.3 apos/datapackage.json
rower/data/ecoinvent 3.3 apos/definitions.json
rower/data/ecoinvent 3.3 consequential/activity_mapping.json
rower/data/ecoinvent 3.3 consequential/datapackage.json
rower/data/ecoinvent 3.3 consequential/definitions.json
rower/data/ecoinvent 3.3 cutoff/activity_mapping.json
rower/data/ecoinvent 3.3 cutoff/datapackage.json
rower/data/ecoinvent 3.3 cutoff/definitions.json
rower/data/ecoinvent 3.4 apos/activity_mapping.json
rower/data/ecoinvent 3.4 apos/datapackage.json
rower/data/ecoinvent 3.4 apos/definitions.json
rower/data/ecoinvent 3.4 consequential/activity_mapping.json
rower/data/ecoinvent 3.4 consequential/datapackage.json
rower/data/ecoinvent 3.4 consequential/definitions.json
rower/data/ecoinvent 3.4 cutoff/activity_mapping.json
rower/data/ecoinvent 3.4 cutoff/datapackage.json
rower/data/ecoinvent 3.4 cutoff/definitions.json
rower/data/ecoinvent 3.5 apos/activity_mapping.json
rower/data/ecoinvent 3.5 apos/datapackage.json
rower/data/ecoinvent 3.5 apos/definitions.json
rower/data/ecoinvent 3.5 consequential/activity_mapping.json
rower/data/ecoinvent 3.5 consequential/datapackage.json
rower/data/ecoinvent 3.5 consequential/definitions.json
rower/data/ecoinvent 3.5 cutoff/activity_mapping.json
rower/data/ecoinvent 3.5 cutoff/datapackage.json
rower/data/ecoinvent 3.5 cutoff/definitions.json
rower/data/ecoinvent generic/datapackage.json
rower/data/ecoinvent generic/definitions.json
rower/data/ecoinvent generic/rows-topomapping.json.bz2
rower-0.2.dist-info/DESCRIPTION.rst
rower-0.2.dist-info/METADATA
rower-0.2.dist-info/RECORD
rower-0.2.dist-info/WHEEL
rower-0.2.dist-info/metadata.json
rower-0.2.dist-info/top_level.txt
