Metadata-Version: 2.0
Name: rower
Version: 0.2
Summary: UNKNOWN
Home-page: https://github.com/PascalLesage/rower
Author: Pascal Lesage
Author-email: pascal.lesage@polymtl.com
License: Copyright (c) 2017, CIRAIG
Requires-Dist: bw2data
Requires-Dist: appdirs
Requires-Dist: pyprind
